[
    {
        "key": "dbln",
        "value": "%7B%2261568900805750%22%3A%22wfcuWq8a%22%7D",
        "domain": "facebook.com",
        "path": "/login/device-based/",
        "hostOnly": false,
        "creation": "2024-11-27T16:06:02.282Z",
        "lastAccessed": "2024-11-27T16:06:02.282Z"
    },
    {
        "key": "datr",
        "value": "LF8aZdqHZJI_jJuetpP08xdL",
        "domain": "facebook.com",
        "path": "/",
        "hostOnly": false,
        "creation": "2024-11-27T16:06:02.282Z",
        "lastAccessed": "2024-11-27T16:06:02.282Z"
    },
    {
        "key": "sb",
        "value": "LF8aZYZ2fG9cZj1S8lfkJRr8",
        "domain": "facebook.com",
        "path": "/",
        "hostOnly": false,
        "creation": "2024-11-27T16:06:02.282Z",
        "lastAccessed": "2024-11-27T16:06:02.282Z"
    },
    {
        "key": "ps_n",
        "value": "1",
        "domain": "facebook.com",
        "path": "/",
        "hostOnly": false,
        "creation": "2024-11-27T16:06:02.282Z",
        "lastAccessed": "2024-11-27T16:06:02.282Z"
    },
    {
        "key": "ps_l",
        "value": "1",
        "domain": "facebook.com",
        "path": "/",
        "hostOnly": false,
        "creation": "2024-11-27T16:06:02.282Z",
        "lastAccessed": "2024-11-27T16:06:02.282Z"
    },
    {
        "key": "dpr",
        "value": "2.1988937854766846",
        "domain": "facebook.com",
        "path": "/",
        "hostOnly": false,
        "creation": "2024-11-27T16:06:02.282Z",
        "lastAccessed": "2024-11-27T16:06:02.282Z"
    },
    {
        "key": "m_pixel_ratio",
        "value": "2",
        "domain": "facebook.com",
        "path": "/",
        "hostOnly": false,
        "creation": "2024-11-27T16:06:02.282Z",
        "lastAccessed": "2024-11-27T16:06:02.282Z"
    },
    {
        "key": "wd",
        "value": "360x680",
        "domain": "facebook.com",
        "path": "/",
        "hostOnly": false,
        "creation": "2024-11-27T16:06:02.282Z",
        "lastAccessed": "2024-11-27T16:06:02.282Z"
    },
    {
        "key": "c_user",
        "value": "61564176657978",
        "domain": "facebook.com",
        "path": "/",
        "hostOnly": false,
        "creation": "2024-11-27T16:06:02.282Z",
        "lastAccessed": "2024-11-27T16:06:02.282Z"
    },
    {
        "key": "fr",
        "value": "1O2iEpG31fDOUpQD1.AWXUUCnB2fOTfP4WzcEmYBpd-oc.BnRApn..AAA.0.0.BnR0Mq.AWWxn0g4dew",
        "domain": "facebook.com",
        "path": "/",
        "hostOnly": false,
        "creation": "2024-11-27T16:06:02.282Z",
        "lastAccessed": "2024-11-27T16:06:02.282Z"
    },
    {
        "key": "xs",
        "value": "6%3Af3X9iw0VsIZW5A%3A2%3A1732723499%3A-1%3A5338",
        "domain": "facebook.com",
        "path": "/",
        "hostOnly": false,
        "creation": "2024-11-27T16:06:02.282Z",
        "lastAccessed": "2024-11-27T16:06:02.282Z"
    },
    {
        "key": "locale",
        "value": "en_GB",
        "domain": "facebook.com",
        "path": "/",
        "hostOnly": false,
        "creation": "2024-11-27T16:06:02.282Z",
        "lastAccessed": "2024-11-27T16:06:02.282Z"
    },
    {
        "key": "fbl_st",
        "value": "100626303%3BT%3A28878725",
        "domain": "facebook.com",
        "path": "/",
        "hostOnly": false,
        "creation": "2024-11-27T16:06:02.282Z",
        "lastAccessed": "2024-11-27T16:06:02.282Z"
    },
    {
        "key": "wl_cbv",
        "value": "v2%3Bclient_version%3A2682%3Btimestamp%3A1732723502",
        "domain": "facebook.com",
        "path": "/",
        "hostOnly": false,
        "creation": "2024-11-27T16:06:02.282Z",
        "lastAccessed": "2024-11-27T16:06:02.282Z"
    },
    {
        "key": "vpd",
        "value": "v1%3B307x360x2",
        "domain": "facebook.com",
        "path": "/",
        "hostOnly": false,
        "creation": "2024-11-27T16:06:02.282Z",
        "lastAccessed": "2024-11-27T16:06:02.282Z"
    }
]
